lab_authentication_retriever/__init__.py
lab_authentication_retriever/_version.py
lab_authentication_retriever/config.py
lab_authentication_retriever/config_logger.py
lab_authentication_retriever/disk_usage.py
lab_authentication_retriever/handlers.py
lab_authentication_retriever-0.1.1.data/data/etc/jupyter/jupyter_server_config.d/lab_authentication_retriever.json
lab_authentication_retriever-0.1.1.data/data/share/jupyter/labextensions/lab-authentication-retriever/package.json
lab_authentication_retriever-0.1.1.data/data/share/jupyter/labextensions/lab-authentication-retriever/static/675.a6166ee1f3ab1b2e5ec3.js
lab_authentication_retriever-0.1.1.data/data/share/jupyter/labextensions/lab-authentication-retriever/static/728.07762a4d56ff003ac491.js
lab_authentication_retriever-0.1.1.data/data/share/jupyter/labextensions/lab-authentication-retriever/static/remoteEntry.f455c9aeebfb52d7acd1.js
lab_authentication_retriever-0.1.1.data/data/share/jupyter/labextensions/lab-authentication-retriever/static/style.js
lab_authentication_retriever-0.1.1.data/data/share/jupyter/labextensions/lab-authentication-retriever/static/third-party-licenses.json
lab_authentication_retriever-0.1.1.data/data/share/jupyter/labextensions/lab-authentication-retriever/install.json
lab_authentication_retriever-0.1.1.dist-info/METADATA
lab_authentication_retriever-0.1.1.dist-info/WHEEL
lab_authentication_retriever-0.1.1.dist-info/licenses/LICENSE
lab_authentication_retriever-0.1.1.dist-info/RECORD
