Metadata-Version: 2.4
Name: lab_authentication_retriever
Version: 0.1.1
Summary: A JupyterLab extension. that interacts with qbraid core and gets authentication details for other front end extension.
Project-URL: Homepage, https://github.com/Nelson-wedefineapps/lab-authentication-retriever.git
Project-URL: Bug Tracker, https://github.com/Nelson-wedefineapps/lab-authentication-retriever.git/issues
Project-URL: Repository, https://github.com/Nelson-wedefineapps/lab-authentication-retriever.git.git
Author-email: nelsonct7 <nelson@wedefineapps.com>
License: BSD 3-Clause License
License-File: LICENSE
Keywords: jupyter,jupyterlab,jupyterlab-extension
Classifier: Framework :: Jupyter
Classifier: Framework :: Jupyter :: JupyterLab
Classifier: Framework :: Jupyter :: JupyterLab :: 4
Classifier: Framework :: Jupyter :: JupyterLab :: Extensions
Classifier: Framework :: Jupyter :: JupyterLab :: Extensions :: Prebuilt
Classifier: License :: OSI Approved :: BSD License
Classifier: Programming Language :: Python
Classifier: Programming Language :: Python :: 3
Classifier: Programming Language :: Python :: 3.9
Classifier: Programming Language :: Python :: 3.10
Classifier: Programming Language :: Python :: 3.11
Classifier: Programming Language :: Python :: 3.12
Classifier: Programming Language :: Python :: 3.13
Requires-Python: >=3.8
Requires-Dist: jupyter-server<3,>=2.4.0
Requires-Dist: qbraid-core
